pynodb/__init__.py
pynodb/database_parser.py
pynodb/example.py
pynodb/notion_database_client.py
pynodb-0.3.dist-info/METADATA
pynodb-0.3.dist-info/WHEEL
pynodb-0.3.dist-info/top_level.txt
pynodb-0.3.dist-info/RECORD
